[{"type":"ActualInterval","date":"2025-03-22","duration":30,"startTime":"2025-03-21T14:00:01Z","endTime":"2025-03-21T14:30:00Z","nemTime":"2025-03-22T00:30:00+10:00","perKwh":43.74346,"renewables":38.013999999999996,"spotPerKwh":16.37003,"channelType":"general","spikeStatus":"none","tariffInformation":{"period":"peak"},"descriptor":"low"},{"type":"ActualInterval","date":"2025-03-22","duration":30,"startTime":"2025-03-21T14:30:01Z","endTime":"2025-03-21T15:00:00Z","nemTime":"2025-03-22T01:00:00+10:00","perKwh":29.69243,"renewables":39.588,"spotPerKwh":14.84099,"channelType":"general","spikeStatus":"none","tariffInformation":{"period":"offPeak"},"descriptor":"veryLow"},{"type":"ActualInterval","date":"2025-03-22","duration":30,"startTime":"2025-03-21T15:00:01Z","endTime":"2025-03-21T15:30:00Z","nemTime":"2025-03-22T01:30:00+10:00","perKwh":30.64989,"renewables":36.331,"spotPerKwh":15.70316,"channelType":"general","spikeStatus":"none","tariffInformation":{"period":"offPeak"},"descriptor":"veryLow"},{"type":"ActualInterval","date":"2025-03-22","duration":30,"startTime":"2025-03-21T15:30:01Z","endTime":"2025-03-21T16:00:00Z","nemTime":"2025-03-22T02:00:00+10:00","perKwh":34.32556,"renewables":32.934000000000005,"spotPerKwh":19.01303,"channelType":"general","spikeStatus":"none","tariffInformation":{"period":"offPeak"},"descriptor":"veryLow"},{"type":"ActualInterval","date":"2025-03-22","duration":30,"startTime":"2025-03-21T16:00:01Z","endTime":"2025-03-21T16:30:00Z","nemTime":"2025-03-22T02:30:00+10:00","perKwh":34.68064,"renewables":29.157,"spotPerKwh":19.33277,"channelType":"general","spikeStatus":"none","tariffInformation":{"period":"offPeak"},"descriptor":"veryLow"},{"type":"ActualInterval","date":"2025-03-22","duration":30,"startTime":"2025-03-21T16:30:01Z","endTime":"2025-03-21T17:00:00Z","nemTime":"2025-03-22T03:00:00+10:00","perKwh":34.4564,"renewables":23.54,"spotPerKwh":19.13085,"channelType":"general","spikeStatus":"none","tariffInformation":{"period":"offPeak"},"descriptor":"veryLow"},{"type":"ActualInterval","date":"2025-03-22","duration":30,"startTime":"2025-03-21T17:00:01Z","endTime":"2025-03-21T17:30:00Z","nemTime":"2025-03-22T03:30:00+10:00","perKwh":33.91834,"renewables":23.493,"spotPerKwh":18.64634,"channelType":"general","spikeStatus":"none","tariffInformation":{"period":"offPeak"},"descriptor":"veryLow"},{"type":"ActualInterval","date":"2025-03-22","duration":30,"startTime":"2025-03-21T17:30:01Z","endTime":"2025-03-21T18:00:00Z","nemTime":"2025-03-22T04:00:00+10:00","perKwh":33.20916,"renewables":25.734,"spotPerKwh":18.00773,"channelType":"general","spikeStatus":"none","tariffInformation":{"period":"offPeak"},"descriptor":"veryLow"},{"type":"ActualInterval","date":"2025-03-22","duration":30,"startTime":"2025-03-21T18:00:01Z","endTime":"2025-03-21T18:30:00Z","nemTime":"2025-03-22T04:30:00+10:00","perKwh":31.56897,"renewables":26.806,"spotPerKwh":16.53078,"channelType":"general","spikeStatus":"none","tariffInformation":{"period":"offPeak"},"descriptor":"veryLow"},{"type":"ActualInterval","date":"2025-03-22","duration":30,"startTime":"2025-03-21T18:30:01Z","endTime":"2025-03-21T19:00:00Z","nemTime":"2025-03-22T05:00:00+10:00","perKwh":32.85427,"renewables":26.136,"spotPerKwh":17.68816,"channelType":"general","spikeStatus":"none","tariffInformation":{"period":"offPeak"},"descriptor":"veryLow"},{"type":"ActualInterval","date":"2025-03-22","duration":30,"startTime":"2025-03-21T19:00:01Z","endTime":"2025-03-21T19:30:00Z","nemTime":"2025-03-22T05:30:00+10:00","perKwh":29.98059,"renewables":21.911,"spotPerKwh":15.10047,"channelType":"general","spikeStatus":"none","tariffInformation":{"period":"offPeak"},"descriptor":"veryLow"},{"type":"ActualInterval","date":"2025-03-22","duration":30,"startTime":"2025-03-21T19:30:01Z","endTime":"2025-03-21T20:00:00Z","nemTime":"2025-03-22T06:00:00+10:00","perKwh":45.08613,"renewables":18.847,"spotPerKwh":17.57908,"channelType":"general","spikeStatus":"none","tariffInformation":{"period":"peak"},"descriptor":"low"},{"type":"ActualInterval","date":"2025-03-22","duration":30,"startTime":"2025-03-21T20:00:01Z","endTime":"2025-03-21T20:30:00Z","nemTime":"2025-03-22T06:30:00+10:00","perKwh":47.10988,"renewables":15.495999999999999,"spotPerKwh":19.40142,"channelType":"general","spikeStatus":"none","tariffInformation":{"period":"peak"},"descriptor":"low"},{"type":"ActualInterval","date":"2025-03-22","duration":30,"startTime":"2025-03-21T20:30:01Z","endTime":"2025-03-21T21:00:00Z","nemTime":"2025-03-22T07:00:00+10:00","perKwh":44.7687,"renewables":15.795,"spotPerKwh":17.29324,"channelType":"general","spikeStatus":"none","tariffInformation":{"period":"peak"},"descriptor":"low"},{"type":"ActualInterval","date":"2025-03-22","duration":30,"startTime":"2025-03-21T21:00:01Z","endTime":"2025-03-21T21:30:00Z","nemTime":"2025-03-22T07:30:00+10:00","perKwh":39.74049,"renewables":23.954,"spotPerKwh":12.76544,"channelType":"general","spikeStatus":"none","tariffInformation":{"period":"peak"},"descriptor":"low"},{"type":"ActualInterval","date":"2025-03-22","duration":30,"startTime":"2025-03-21T21:30:01Z","endTime":"2025-03-21T22:00:00Z","nemTime":"2025-03-22T08:00:00+10:00","perKwh":34.31487,"renewables":36.592999999999996,"spotPerKwh":7.87978,"channelType":"general","spikeStatus":"none","tariffInformation":{"period":"peak"},"descriptor":"veryLow"},{"type":"ActualInterval","date":"2025-03-22","duration":30,"startTime":"2025-03-21T22:00:01Z","endTime":"2025-03-21T22:30:00Z","nemTime":"2025-03-22T08:30:00+10:00","perKwh":36.82405,"renewables":54.668000000000006,"spotPerKwh":10.13925,"channelType":"general","spikeStatus":"none","tariffInformation":{"period":"peak"},"descriptor":"veryLow"},{"type":"ActualInterval","date":"2025-03-22","duration":30,"startTime":"2025-03-21T22:30:01Z","endTime":"2025-03-21T23:00:00Z","nemTime":"2025-03-22T09:00:00+10:00","perKwh":24.76649,"renewables":70.24000000000001,"spotPerKwh":-0.71834,"channelType":"general","spikeStatus":"none","tariffInformation":{"period":"peak"},"descriptor":"veryLow"},{"type":"ActualInterval","date":"2025-03-22","duration":30,"startTime":"2025-03-21T23:00:01Z","endTime":"2025-03-21T23:30:00Z","nemTime":"2025-03-22T09:30:00+10:00","perKwh":22.21919,"renewables":81.862,"spotPerKwh":-3.01213,"channelType":"general","spikeStatus":"none","tariffInformation":{"period":"peak"},"descriptor":"veryLow"},{"type":"ActualInterval","date":"2025-03-22","duration":30,"startTime":"2025-03-21T23:30:01Z","endTime":"2025-03-22T00:00:00Z","nemTime":"2025-03-22T10:00:00+10:00","perKwh":-1.57301,"renewables":84.33500000000001,"spotPerKwh":-9.59842,"channelType":"general","spikeStatus":"none","tariffInformation":{"period":"solarSponge"},"descriptor":"extremelyLow"},{"type":"ActualInterval","date":"2025-03-22","duration":30,"startTime":"2025-03-22T00:00:01Z","endTime":"2025-03-22T00:30:00Z","nemTime":"2025-03-22T10:30:00+10:00","perKwh":2.323,"renewables":91.228,"spotPerKwh":-6.09014,"channelType":"general","spikeStatus":"none","tariffInformation":{"period":"solarSponge"},"descriptor":"extremelyLow"},{"type":"ActualInterval","date":"2025-03-22","duration":30,"startTime":"2025-03-22T00:30:01Z","endTime":"2025-03-22T01:00:00Z","nemTime":"2025-03-22T11:00:00+10:00","perKwh":-1.86578,"renewables":81.142,"spotPerKwh":-9.86205,"channelType":"general","spikeStatus":"none","tariffInformation":{"period":"solarSponge"},"descriptor":"extremelyLow"},{"type":"ActualInterval","date":"2025-03-22","duration":30,"startTime":"2025-03-22T01:00:01Z","endTime":"2025-03-22T01:30:00Z","nemTime":"2025-03-22T11:30:00+10:00","perKwh":1.26491,"renewables":83.98400000000001,"spotPerKwh":-7.04293,"channelType":"general","spikeStatus":"none","tariffInformation":{"period":"solarSponge"},"descriptor":"extremelyLow"},{"type":"ActualInterval","date":"2025-03-22","duration":30,"startTime":"2025-03-22T01:30:01Z","endTime":"2025-03-22T02:00:00Z","nemTime":"2025-03-22T12:00:00+10:00","perKwh":2.80951,"renewables":88.98,"spotPerKwh":-5.65205,"channelType":"general","spikeStatus":"none","tariffInformation":{"period":"solarSponge"},"descriptor":"extremelyLow"},{"type":"ActualInterval","date":"2025-03-22","duration":30,"startTime":"2025-03-22T02:00:01Z","endTime":"2025-03-22T02:30:00Z","nemTime":"2025-03-22T12:30:00+10:00","perKwh":-1.77545,"renewables":89.29599999999999,"spotPerKwh":-9.78071,"channelType":"general","spikeStatus":"none","tariffInformation":{"period":"solarSponge"},"descriptor":"extremelyLow"},{"type":"ActualInterval","date":"2025-03-22","duration":30,"startTime":"2025-03-22T02:30:01Z","endTime":"2025-03-22T03:00:00Z","nemTime":"2025-03-22T13:00:00+10:00","perKwh":3.34388,"renewables":94.172,"spotPerKwh":-5.17086,"channelType":"general","spikeStatus":"none","tariffInformation":{"period":"solarSponge"},"descriptor":"extremelyLow"},{"type":"ActualInterval","date":"2025-03-22","duration":30,"startTime":"2025-03-22T03:00:01Z","endTime":"2025-03-22T03:30:00Z","nemTime":"2025-03-22T13:30:00+10:00","perKwh":2.34246,"renewables":95.36200000000001,"spotPerKwh":-6.07262,"channelType":"general","spikeStatus":"none","tariffInformation":{"period":"solarSponge"},"descriptor":"extremelyLow"},{"type":"ActualInterval","date":"2025-03-22","duration":30,"startTime":"2025-03-22T03:30:01Z","endTime":"2025-03-22T04:00:00Z","nemTime":"2025-03-22T14:00:00+10:00","perKwh":1.78063,"renewables":95.854,"spotPerKwh":-6.57853,"channelType":"general","spikeStatus":"none","tariffInformation":{"period":"solarSponge"},"descriptor":"extremelyLow"},{"type":"ActualInterval","date":"2025-03-22","duration":30,"startTime":"2025-03-22T04:00:01Z","endTime":"2025-03-22T04:30:00Z","nemTime":"2025-03-22T14:30:00+10:00","perKwh":3.05089,"renewables":92.023,"spotPerKwh":-5.43469,"channelType":"general","spikeStatus":"none","tariffInformation":{"period":"solarSponge"},"descriptor":"extremelyLow"},{"type":"ActualInterval","date":"2025-03-22","duration":30,"startTime":"2025-03-22T04:30:01Z","endTime":"2025-03-22T05:00:00Z","nemTime":"2025-03-22T15:00:00+10:00","perKwh":21.46828,"renewables":95.095,"spotPerKwh":-3.68831,"channelType":"general","spikeStatus":"none","tariffInformation":{"period":"peak"},"descriptor":"veryLow"},{"type":"ActualInterval","date":"2025-03-22","duration":30,"startTime":"2025-03-22T05:00:01Z","endTime":"2025-03-22T05:30:00Z","nemTime":"2025-03-22T15:30:00+10:00","perKwh":22.55569,"renewables":98.804,"spotPerKwh":-2.70912,"channelType":"general","spikeStatus":"none","tariffInformation":{"period":"peak"},"descriptor":"veryLow"},{"type":"ActualInterval","date":"2025-03-22","duration":30,"startTime":"2025-03-22T05:30:01Z","endTime":"2025-03-22T06:00:00Z","nemTime":"2025-03-22T16:00:00+10:00","perKwh":25.25163,"renewables":104.119,"spotPerKwh":-0.28148,"channelType":"general","spikeStatus":"none","tariffInformation":{"period":"peak"},"descriptor":"veryLow"},{"type":"ActualInterval","date":"2025-03-22","duration":30,"startTime":"2025-03-22T06:00:01Z","endTime":"2025-03-22T06:30:00Z","nemTime":"2025-03-22T16:30:00+10:00","perKwh":31.43108,"renewables":101.64999999999999,"spotPerKwh":5.28299,"channelType":"general","spikeStatus":"none","tariffInformation":{"period":"peak"},"descriptor":"veryLow"},{"type":"ActualInterval","date":"2025-03-22","duration":30,"startTime":"2025-03-22T06:30:01Z","endTime":"2025-03-22T07:00:00Z","nemTime":"2025-03-22T17:00:00+10:00","perKwh":34.99592,"renewables":85.004,"spotPerKwh":8.49305,"channelType":"general","spikeStatus":"none","tariffInformation":{"period":"peak"},"descriptor":"veryLow"},{"type":"ActualInterval","date":"2025-03-22","duration":30,"startTime":"2025-03-22T07:00:01Z","endTime":"2025-03-22T07:30:00Z","nemTime":"2025-03-22T17:30:00+10:00","perKwh":42.35472,"renewables":73.882,"spotPerKwh":15.1195,"channelType":"general","spikeStatus":"none","tariffInformation":{"period":"peak"},"descriptor":"low"},{"type":"ActualInterval","date":"2025-03-22","duration":30,"startTime":"2025-03-22T07:30:01Z","endTime":"2025-03-22T08:00:00Z","nemTime":"2025-03-22T18:00:00+10:00","perKwh":34.99986,"renewables":57.706999999999994,"spotPerKwh":8.4966,"channelType":"general","spikeStatus":"none","tariffInformation":{"period":"peak"},"descriptor":"veryLow"},{"type":"ActualInterval","date":"2025-03-22","duration":30,"startTime":"2025-03-22T08:00:01Z","endTime":"2025-03-22T08:30:00Z","nemTime":"2025-03-22T18:30:00+10:00","perKwh":44.46611,"renewables":46.798,"spotPerKwh":17.02076,"channelType":"general","spikeStatus":"none","tariffInformation":{"period":"peak"},"descriptor":"low"},{"type":"ActualInterval","date":"2025-03-22","duration":30,"startTime":"2025-03-22T08:30:01Z","endTime":"2025-03-22T09:00:00Z","nemTime":"2025-03-22T19:00:00+10:00","perKwh":45.21323,"renewables":41.386,"spotPerKwh":17.69353,"channelType":"general","spikeStatus":"none","tariffInformation":{"period":"peak"},"descriptor":"low"},{"type":"ActualInterval","date":"2025-03-22","duration":30,"startTime":"2025-03-22T09:00:01Z","endTime":"2025-03-22T09:30:00Z","nemTime":"2025-03-22T19:30:00+10:00","perKwh":42.64027,"renewables":43.663999999999994,"spotPerKwh":15.37663,"channelType":"general","spikeStatus":"none","tariffInformation":{"period":"peak"},"descriptor":"low"},{"type":"ActualInterval","date":"2025-03-22","duration":30,"startTime":"2025-03-22T09:30:01Z","endTime":"2025-03-22T10:00:00Z","nemTime":"2025-03-22T20:00:00+10:00","perKwh":42.0949,"renewables":48.479,"spotPerKwh":14.88554,"channelType":"general","spikeStatus":"none","tariffInformation":{"period":"peak"},"descriptor":"low"},{"type":"ActualInterval","date":"2025-03-22","duration":30,"startTime":"2025-03-22T10:00:01Z","endTime":"2025-03-22T10:30:00Z","nemTime":"2025-03-22T20:30:00+10:00","perKwh":39.55819,"renewables":54.806999999999995,"spotPerKwh":12.60128,"channelType":"general","spikeStatus":"none","tariffInformation":{"period":"peak"},"descriptor":"low"},{"type":"ActualInterval","date":"2025-03-22","duration":30,"startTime":"2025-03-22T10:30:01Z","endTime":"2025-03-22T11:00:00Z","nemTime":"2025-03-22T21:00:00+10:00","perKwh":38.91309,"renewables":56.058,"spotPerKwh":12.02038,"channelType":"general","spikeStatus":"none","tariffInformation":{"period":"peak"},"descriptor":"veryLow"},{"type":"ActualInterval","date":"2025-03-22","duration":30,"startTime":"2025-03-22T11:00:01Z","endTime":"2025-03-22T11:30:00Z","nemTime":"2025-03-22T21:30:00+10:00","perKwh":39.33775,"renewables":56.389,"spotPerKwh":12.40278,"channelType":"general","spikeStatus":"none","tariffInformation":{"period":"peak"},"descriptor":"veryLow"},{"type":"ActualInterval","date":"2025-03-22","duration":30,"startTime":"2025-03-22T11:30:01Z","endTime":"2025-03-22T12:00:00Z","nemTime":"2025-03-22T22:00:00+10:00","perKwh":37.6539,"renewables":59.829,"spotPerKwh":10.88651,"channelType":"general","spikeStatus":"none","tariffInformation":{"period":"peak"},"descriptor":"veryLow"},{"type":"ActualInterval","date":"2025-03-22","duration":30,"startTime":"2025-03-22T12:00:01Z","endTime":"2025-03-22T12:30:00Z","nemTime":"2025-03-22T22:30:00+10:00","perKwh":37.1998,"renewables":58.498000000000005,"spotPerKwh":10.4776,"channelType":"general","spikeStatus":"none","tariffInformation":{"period":"peak"},"descriptor":"veryLow"},{"type":"ActualInterval","date":"2025-03-22","duration":30,"startTime":"2025-03-22T12:30:01Z","endTime":"2025-03-22T13:00:00Z","nemTime":"2025-03-22T23:00:00+10:00","perKwh":39.13319,"renewables":55.593,"spotPerKwh":12.21858,"channelType":"general","spikeStatus":"none","tariffInformation":{"period":"peak"},"descriptor":"veryLow"},{"type":"ActualInterval","date":"2025-03-22","duration":30,"startTime":"2025-03-22T13:00:01Z","endTime":"2025-03-22T13:30:00Z","nemTime":"2025-03-22T23:30:00+10:00","perKwh":38.96347,"renewables":54.237,"spotPerKwh":12.06575,"channelType":"general","spikeStatus":"none","tariffInformation":{"period":"peak"},"descriptor":"veryLow"},{"type":"ActualInterval","date":"2025-03-22","duration":30,"startTime":"2025-03-22T13:30:01Z","endTime":"2025-03-22T14:00:00Z","nemTime":"2025-03-23T00:00:00+10:00","perKwh":38.78632,"renewables":53.825,"spotPerKwh":11.90623,"channelType":"general","spikeStatus":"none","tariffInformation":{"period":"peak"},"descriptor":"veryLow"},{"type":"ActualInterval","date":"2025-03-22","duration":30,"startTime":"2025-03-21T14:00:01Z","endTime":"2025-03-21T14:30:00Z","nemTime":"2025-03-22T00:30:00+10:00","perKwh":31.39046,"renewables":38.013999999999996,"spotPerKwh":16.37003,"channelType":"controlledLoad","spikeStatus":"none","tariffInformation":{"period":"offPeak","season":"default"},"descriptor":"low"},{"type":"ActualInterval","date":"2025-03-22","duration":30,"startTime":"2025-03-21T14:30:01Z","endTime":"2025-03-21T15:00:00Z","nemTime":"2025-03-22T01:00:00+10:00","perKwh":29.69243,"renewables":39.588,"spotPerKwh":14.84099,"channelType":"controlledLoad","spikeStatus":"none","tariffInformation":{"period":"offPeak","season":"default"},"descriptor":"low"},{"type":"ActualInterval","date":"2025-03-22","duration":30,"startTime":"2025-03-21T15:00:01Z","endTime":"2025-03-21T15:30:00Z","nemTime":"2025-03-22T01:30:00+10:00","perKwh":30.64989,"renewables":36.331,"spotPerKwh":15.70316,"channelType":"controlledLoad","spikeStatus":"none","tariffInformation":{"period":"offPeak","season":"default"},"descriptor":"low"},{"type":"ActualInterval","date":"2025-03-22","duration":30,"startTime":"2025-03-21T15:30:01Z","endTime":"2025-03-21T16:00:00Z","nemTime":"2025-03-22T02:00:00+10:00","perKwh":34.32556,"renewables":32.934000000000005,"spotPerKwh":19.01303,"channelType":"controlledLoad","spikeStatus":"none","tariffInformation":{"period":"offPeak","season":"default"},"descriptor":"low"},{"type":"ActualInterval","date":"2025-03-22","duration":30,"startTime":"2025-03-21T16:00:01Z","endTime":"2025-03-21T16:30:00Z","nemTime":"2025-03-22T02:30:00+10:00","perKwh":34.68064,"renewables":29.157,"spotPerKwh":19.33277,"channelType":"controlledLoad","spikeStatus":"none","tariffInformation":{"period":"offPeak","season":"default"},"descriptor":"low"},{"type":"ActualInterval","date":"2025-03-22","duration":30,"startTime":"2025-03-21T16:30:01Z","endTime":"2025-03-21T17:00:00Z","nemTime":"2025-03-22T03:00:00+10:00","perKwh":34.4564,"renewables":23.54,"spotPerKwh":19.13085,"channelType":"controlledLoad","spikeStatus":"none","tariffInformation":{"period":"offPeak","season":"default"},"descriptor":"low"},{"type":"ActualInterval","date":"2025-03-22","duration":30,"startTime":"2025-03-21T17:00:01Z","endTime":"2025-03-21T17:30:00Z","nemTime":"2025-03-22T03:30:00+10:00","perKwh":33.91834,"renewables":23.493,"spotPerKwh":18.64634,"channelType":"controlledLoad","spikeStatus":"none","tariffInformation":{"period":"offPeak","season":"default"},"descriptor":"low"},{"type":"ActualInterval","date":"2025-03-22","duration":30,"startTime":"2025-03-21T17:30:01Z","endTime":"2025-03-21T18:00:00Z","nemTime":"2025-03-22T04:00:00+10:00","perKwh":33.20916,"renewables":25.734,"spotPerKwh":18.00773,"channelType":"controlledLoad","spikeStatus":"none","tariffInformation":{"period":"offPeak","season":"default"},"descriptor":"low"},{"type":"ActualInterval","date":"2025-03-22","duration":30,"startTime":"2025-03-21T18:00:01Z","endTime":"2025-03-21T18:30:00Z","nemTime":"2025-03-22T04:30:00+10:00","perKwh":31.56897,"renewables":26.806,"spotPerKwh":16.53078,"channelType":"controlledLoad","spikeStatus":"none","tariffInformation":{"period":"offPeak","season":"default"},"descriptor":"low"},{"type":"ActualInterval","date":"2025-03-22","duration":30,"startTime":"2025-03-21T18:30:01Z","endTime":"2025-03-21T19:00:00Z","nemTime":"2025-03-22T05:00:00+10:00","perKwh":32.85427,"renewables":26.136,"spotPerKwh":17.68816,"channelType":"controlledLoad","spikeStatus":"none","tariffInformation":{"period":"offPeak","season":"default"},"descriptor":"low"},{"type":"ActualInterval","date":"2025-03-22","duration":30,"startTime":"2025-03-21T19:00:01Z","endTime":"2025-03-21T19:30:00Z","nemTime":"2025-03-22T05:30:00+10:00","perKwh":29.98059,"renewables":21.911,"spotPerKwh":15.10047,"channelType":"controlledLoad","spikeStatus":"none","tariffInformation":{"period":"offPeak","season":"default"},"descriptor":"low"},{"type":"ActualInterval","date":"2025-03-22","duration":30,"startTime":"2025-03-21T19:30:01Z","endTime":"2025-03-21T20:00:00Z","nemTime":"2025-03-22T06:00:00+10:00","perKwh":32.73313,"renewables":18.847,"spotPerKwh":17.57908,"channelType":"controlledLoad","spikeStatus":"none","tariffInformation":{"period":"offPeak","season":"default"},"descriptor":"low"},{"type":"ActualInterval","date":"2025-03-22","duration":30,"startTime":"2025-03-21T20:00:01Z","endTime":"2025-03-21T20:30:00Z","nemTime":"2025-03-22T06:30:00+10:00","perKwh":34.75688,"renewables":15.495999999999999,"spotPerKwh":19.40142,"channelType":"controlledLoad","spikeStatus":"none","tariffInformation":{"period":"offPeak","season":"default"},"descriptor":"low"},{"type":"ActualInterval","date":"2025-03-22","duration":30,"startTime":"2025-03-21T20:30:01Z","endTime":"2025-03-21T21:00:00Z","nemTime":"2025-03-22T07:00:00+10:00","perKwh":32.4157,"renewables":15.795,"spotPerKwh":17.29324,"channelType":"controlledLoad","spikeStatus":"none","tariffInformation":{"period":"offPeak","season":"default"},"descriptor":"low"},{"type":"ActualInterval","date":"2025-03-22","duration":30,"startTime":"2025-03-21T21:00:01Z","endTime":"2025-03-21T21:30:00Z","nemTime":"2025-03-22T07:30:00+10:00","perKwh":39.74049,"renewables":23.954,"spotPerKwh":12.76544,"channelType":"controlledLoad","spikeStatus":"none","tariffInformation":{"period":"peak","season":"default"},"descriptor":"neutral"},{"type":"ActualInterval","date":"2025-03-22","duration":30,"startTime":"2025-03-21T21:30:01Z","endTime":"2025-03-21T22:00:00Z","nemTime":"2025-03-22T08:00:00+10:00","perKwh":34.31487,"renewables":36.592999999999996,"spotPerKwh":7.87978,"channelType":"controlledLoad","spikeStatus":"none","tariffInformation":{"period":"peak","season":"default"},"descriptor":"low"},{"type":"ActualInterval","date":"2025-03-22","duration":30,"startTime":"2025-03-21T22:00:01Z","endTime":"2025-03-21T22:30:00Z","nemTime":"2025-03-22T08:30:00+10:00","perKwh":36.82405,"renewables":54.668000000000006,"spotPerKwh":10.13925,"channelType":"controlledLoad","spikeStatus":"none","tariffInformation":{"period":"peak","season":"default"},"descriptor":"neutral"},{"type":"ActualInterval","date":"2025-03-22","duration":30,"startTime":"2025-03-21T22:30:01Z","endTime":"2025-03-21T23:00:00Z","nemTime":"2025-03-22T09:00:00+10:00","perKwh":24.76649,"renewables":70.24000000000001,"spotPerKwh":-0.71834,"channelType":"controlledLoad","spikeStatus":"none","tariffInformation":{"period":"peak","season":"default"},"descriptor":"extremelyLow"},{"type":"ActualInterval","date":"2025-03-22","duration":30,"startTime":"2025-03-21T23:00:01Z","endTime":"2025-03-21T23:30:00Z","nemTime":"2025-03-22T09:30:00+10:00","perKwh":22.21919,"renewables":81.862,"spotPerKwh":-3.01213,"channelType":"controlledLoad","spikeStatus":"none","tariffInformation":{"period":"peak","season":"default"},"descriptor":"extremelyLow"},{"type":"ActualInterval","date":"2025-03-22","duration":30,"startTime":"2025-03-21T23:30:01Z","endTime":"2025-03-22T00:00:00Z","nemTime":"2025-03-22T10:00:00+10:00","perKwh":14.90499,"renewables":84.33500000000001,"spotPerKwh":-9.59842,"channelType":"controlledLoad","spikeStatus":"none","tariffInformation":{"period":"peak","season":"default"},"descriptor":"extremelyLow"},{"type":"ActualInterval","date":"2025-03-22","duration":30,"startTime":"2025-03-22T00:00:01Z","endTime":"2025-03-22T00:30:00Z","nemTime":"2025-03-22T10:30:00+10:00","perKwh":2.323,"renewables":91.228,"spotPerKwh":-6.09014,"channelType":"controlledLoad","spikeStatus":"none","tariffInformation":{"period":"solarSponge","season":"default"},"descriptor":"extremelyLow"},{"type":"ActualInterval","date":"2025-03-22","duration":30,"startTime":"2025-03-22T00:30:01Z","endTime":"2025-03-22T01:00:00Z","nemTime":"2025-03-22T11:00:00+10:00","perKwh":-1.86578,"renewables":81.142,"spotPerKwh":-9.86205,"channelType":"controlledLoad","spikeStatus":"none","tariffInformation":{"period":"solarSponge","season":"default"},"descriptor":"extremelyLow"},{"type":"ActualInterval","date":"2025-03-22","duration":30,"startTime":"2025-03-22T01:00:01Z","endTime":"2025-03-22T01:30:00Z","nemTime":"2025-03-22T11:30:00+10:00","perKwh":1.26491,"renewables":83.98400000000001,"spotPerKwh":-7.04293,"channelType":"controlledLoad","spikeStatus":"none","tariffInformation":{"period":"solarSponge","season":"default"},"descriptor":"extremelyLow"},{"type":"ActualInterval","date":"2025-03-22","duration":30,"startTime":"2025-03-22T01:30:01Z","endTime":"2025-03-22T02:00:00Z","nemTime":"2025-03-22T12:00:00+10:00","perKwh":2.80951,"renewables":88.98,"spotPerKwh":-5.65205,"channelType":"controlledLoad","spikeStatus":"none","tariffInformation":{"period":"solarSponge","season":"default"},"descriptor":"extremelyLow"},{"type":"ActualInterval","date":"2025-03-22","duration":30,"startTime":"2025-03-22T02:00:01Z","endTime":"2025-03-22T02:30:00Z","nemTime":"2025-03-22T12:30:00+10:00","perKwh":-1.77545,"renewables":89.29599999999999,"spotPerKwh":-9.78071,"channelType":"controlledLoad","spikeStatus":"none","tariffInformation":{"period":"solarSponge","season":"default"},"descriptor":"extremelyLow"},{"type":"ActualInterval","date":"2025-03-22","duration":30,"startTime":"2025-03-22T02:30:01Z","endTime":"2025-03-22T03:00:00Z","nemTime":"2025-03-22T13:00:00+10:00","perKwh":3.34388,"renewables":94.172,"spotPerKwh":-5.17086,"channelType":"controlledLoad","spikeStatus":"none","tariffInformation":{"period":"solarSponge","season":"default"},"descriptor":"extremelyLow"},{"type":"ActualInterval","date":"2025-03-22","duration":30,"startTime":"2025-03-22T03:00:01Z","endTime":"2025-03-22T03:30:00Z","nemTime":"2025-03-22T13:30:00+10:00","perKwh":2.34246,"renewables":95.36200000000001,"spotPerKwh":-6.07262,"channelType":"controlledLoad","spikeStatus":"none","tariffInformation":{"period":"solarSponge","season":"default"},"descriptor":"extremelyLow"},{"type":"ActualInterval","date":"2025-03-22","duration":30,"startTime":"2025-03-22T03:30:01Z","endTime":"2025-03-22T04:00:00Z","nemTime":"2025-03-22T14:00:00+10:00","perKwh":1.78063,"renewables":95.854,"spotPerKwh":-6.57853,"channelType":"controlledLoad","spikeStatus":"none","tariffInformation":{"period":"solarSponge","season":"default"},"descriptor":"extremelyLow"},{"type":"ActualInterval","date":"2025-03-22","duration":30,"startTime":"2025-03-22T04:00:01Z","endTime":"2025-03-22T04:30:00Z","nemTime":"2025-03-22T14:30:00+10:00","perKwh":3.05089,"renewables":92.023,"spotPerKwh":-5.43469,"channelType":"controlledLoad","spikeStatus":"none","tariffInformation":{"period":"solarSponge","season":"default"},"descriptor":"extremelyLow"},{"type":"ActualInterval","date":"2025-03-22","duration":30,"startTime":"2025-03-22T04:30:01Z","endTime":"2025-03-22T05:00:00Z","nemTime":"2025-03-22T15:00:00+10:00","perKwh":4.99028,"renewables":95.095,"spotPerKwh":-3.68831,"channelType":"controlledLoad","spikeStatus":"none","tariffInformation":{"period":"solarSponge","season":"default"},"descriptor":"extremelyLow"},{"type":"ActualInterval","date":"2025-03-22","duration":30,"startTime":"2025-03-22T05:00:01Z","endTime":"2025-03-22T05:30:00Z","nemTime":"2025-03-22T15:30:00+10:00","perKwh":6.07769,"renewables":98.804,"spotPerKwh":-2.70912,"channelType":"controlledLoad","spikeStatus":"none","tariffInformation":{"period":"solarSponge","season":"default"},"descriptor":"extremelyLow"},{"type":"ActualInterval","date":"2025-03-22","duration":30,"startTime":"2025-03-22T05:30:01Z","endTime":"2025-03-22T06:00:00Z","nemTime":"2025-03-22T16:00:00+10:00","perKwh":8.77363,"renewables":104.119,"spotPerKwh":-0.28148,"channelType":"controlledLoad","spikeStatus":"none","tariffInformation":{"period":"solarSponge","season":"default"},"descriptor":"extremelyLow"},{"type":"ActualInterval","date":"2025-03-22","duration":30,"startTime":"2025-03-22T06:00:01Z","endTime":"2025-03-22T06:30:00Z","nemTime":"2025-03-22T16:30:00+10:00","perKwh":31.43108,"renewables":101.64999999999999,"spotPerKwh":5.28299,"channelType":"controlledLoad","spikeStatus":"none","tariffInformation":{"period":"peak","season":"default"},"descriptor":"low"},{"type":"ActualInterval","date":"2025-03-22","duration":30,"startTime":"2025-03-22T06:30:01Z","endTime":"2025-03-22T07:00:00Z","nemTime":"2025-03-22T17:00:00+10:00","perKwh":34.99592,"renewables":85.004,"spotPerKwh":8.49305,"channelType":"controlledLoad","spikeStatus":"none","tariffInformation":{"period":"peak","season":"default"},"descriptor":"low"},{"type":"ActualInterval","date":"2025-03-22","duration":30,"startTime":"2025-03-22T07:00:01Z","endTime":"2025-03-22T07:30:00Z","nemTime":"2025-03-22T17:30:00+10:00","perKwh":42.35472,"renewables":73.882,"spotPerKwh":15.1195,"channelType":"controlledLoad","spikeStatus":"none","tariffInformation":{"period":"peak","season":"default"},"descriptor":"neutral"},{"type":"ActualInterval","date":"2025-03-22","duration":30,"startTime":"2025-03-22T07:30:01Z","endTime":"2025-03-22T08:00:00Z","nemTime":"2025-03-22T18:00:00+10:00","perKwh":34.99986,"renewables":57.706999999999994,"spotPerKwh":8.4966,"channelType":"controlledLoad","spikeStatus":"none","tariffInformation":{"period":"peak","season":"default"},"descriptor":"low"},{"type":"ActualInterval","date":"2025-03-22","duration":30,"startTime":"2025-03-22T08:00:01Z","endTime":"2025-03-22T08:30:00Z","nemTime":"2025-03-22T18:30:00+10:00","perKwh":44.46611,"renewables":46.798,"spotPerKwh":17.02076,"channelType":"controlledLoad","spikeStatus":"none","tariffInformation":{"period":"peak","season":"default"},"descriptor":"neutral"},{"type":"ActualInterval","date":"2025-03-22","duration":30,"startTime":"2025-03-22T08:30:01Z","endTime":"2025-03-22T09:00:00Z","nemTime":"2025-03-22T19:00:00+10:00","perKwh":45.21323,"renewables":41.386,"spotPerKwh":17.69353,"channelType":"controlledLoad","spikeStatus":"none","tariffInformation":{"period":"peak","season":"default"},"descriptor":"neutral"},{"type":"ActualInterval","date":"2025-03-22","duration":30,"startTime":"2025-03-22T09:00:01Z","endTime":"2025-03-22T09:30:00Z","nemTime":"2025-03-22T19:30:00+10:00","perKwh":42.64027,"renewables":43.663999999999994,"spotPerKwh":15.37663,"channelType":"controlledLoad","spikeStatus":"none","tariffInformation":{"period":"peak","season":"default"},"descriptor":"neutral"},{"type":"ActualInterval","date":"2025-03-22","duration":30,"startTime":"2025-03-22T09:30:01Z","endTime":"2025-03-22T10:00:00Z","nemTime":"2025-03-22T20:00:00+10:00","perKwh":42.0949,"renewables":48.479,"spotPerKwh":14.88554,"channelType":"controlledLoad","spikeStatus":"none","tariffInformation":{"period":"peak","season":"default"},"descriptor":"neutral"},{"type":"ActualInterval","date":"2025-03-22","duration":30,"startTime":"2025-03-22T10:00:01Z","endTime":"2025-03-22T10:30:00Z","nemTime":"2025-03-22T20:30:00+10:00","perKwh":39.55819,"renewables":54.806999999999995,"spotPerKwh":12.60128,"channelType":"controlledLoad","spikeStatus":"none","tariffInformation":{"period":"peak","season":"default"},"descriptor":"neutral"},{"type":"ActualInterval","date":"2025-03-22","duration":30,"startTime":"2025-03-22T10:30:01Z","endTime":"2025-03-22T11:00:00Z","nemTime":"2025-03-22T21:00:00+10:00","perKwh":38.91309,"renewables":56.058,"spotPerKwh":12.02038,"channelType":"controlledLoad","spikeStatus":"none","tariffInformation":{"period":"peak","season":"default"},"descriptor":"neutral"},{"type":"ActualInterval","date":"2025-03-22","duration":30,"startTime":"2025-03-22T11:00:01Z","endTime":"2025-03-22T11:30:00Z","nemTime":"2025-03-22T21:30:00+10:00","perKwh":39.33775,"renewables":56.389,"spotPerKwh":12.40278,"channelType":"controlledLoad","spikeStatus":"none","tariffInformation":{"period":"peak","season":"default"},"descriptor":"neutral"},{"type":"ActualInterval","date":"2025-03-22","duration":30,"startTime":"2025-03-22T11:30:01Z","endTime":"2025-03-22T12:00:00Z","nemTime":"2025-03-22T22:00:00+10:00","perKwh":37.6539,"renewables":59.829,"spotPerKwh":10.88651,"channelType":"controlledLoad","spikeStatus":"none","tariffInformation":{"period":"peak","season":"default"},"descriptor":"neutral"},{"type":"ActualInterval","date":"2025-03-22","duration":30,"startTime":"2025-03-22T12:00:01Z","endTime":"2025-03-22T12:30:00Z","nemTime":"2025-03-22T22:30:00+10:00","perKwh":37.1998,"renewables":58.498000000000005,"spotPerKwh":10.4776,"channelType":"controlledLoad","spikeStatus":"none","tariffInformation":{"period":"peak","season":"default"},"descriptor":"neutral"},{"type":"ActualInterval","date":"2025-03-22","duration":30,"startTime":"2025-03-22T12:30:01Z","endTime":"2025-03-22T13:00:00Z","nemTime":"2025-03-22T23:00:00+10:00","perKwh":39.13319,"renewables":55.593,"spotPerKwh":12.21858,"channelType":"controlledLoad","spikeStatus":"none","tariffInformation":{"period":"peak","season":"default"},"descriptor":"neutral"},{"type":"ActualInterval","date":"2025-03-22","duration":30,"startTime":"2025-03-22T13:00:01Z","endTime":"2025-03-22T13:30:00Z","nemTime":"2025-03-22T23:30:00+10:00","perKwh":38.96347,"renewables":54.237,"spotPerKwh":12.06575,"channelType":"controlledLoad","spikeStatus":"none","tariffInformation":{"period":"peak","season":"default"},"descriptor":"neutral"},{"type":"ActualInterval","date":"2025-03-22","duration":30,"startTime":"2025-03-22T13:30:01Z","endTime":"2025-03-22T14:00:00Z","nemTime":"2025-03-23T00:00:00+10:00","perKwh":38.78632,"renewables":53.825,"spotPerKwh":11.90623,"channelType":"controlledLoad","spikeStatus":"none","tariffInformation":{"period":"peak","season":"default"},"descriptor":"neutral"},{"type":"ActualInterval","date":"2025-03-22","duration":30,"startTime":"2025-03-21T14:00:01Z","endTime":"2025-03-21T14:30:00Z","nemTime":"2025-03-22T00:30:00+10:00","perKwh":-16.52658,"renewables":38.013999999999996,"spotPerKwh":16.37003,"channelType":"feedIn","spikeStatus":"none","descriptor":"high"},{"type":"ActualInterval","date":"2025-03-22","duration":30,"startTime":"2025-03-21T14:30:01Z","endTime":"2025-03-21T15:00:00Z","nemTime":"2025-03-22T01:00:00+10:00","perKwh":-14.98292,"renewables":39.588,"spotPerKwh":14.84099,"channelType":"feedIn","spikeStatus":"none","descriptor":"high"},{"type":"ActualInterval","date":"2025-03-22","duration":30,"startTime":"2025-03-21T15:00:01Z","endTime":"2025-03-21T15:30:00Z","nemTime":"2025-03-22T01:30:00+10:00","perKwh":-15.85333,"renewables":36.331,"spotPerKwh":15.70316,"channelType":"feedIn","spikeStatus":"none","descriptor":"high"},{"type":"ActualInterval","date":"2025-03-22","duration":30,"startTime":"2025-03-21T15:30:01Z","endTime":"2025-03-21T16:00:00Z","nemTime":"2025-03-22T02:00:00+10:00","perKwh":-19.19486,"renewables":32.934000000000005,"spotPerKwh":19.01303,"channelType":"feedIn","spikeStatus":"none","descriptor":"high"},{"type":"ActualInterval","date":"2025-03-22","duration":30,"startTime":"2025-03-21T16:00:01Z","endTime":"2025-03-21T16:30:00Z","nemTime":"2025-03-22T02:30:00+10:00","perKwh":-19.51765,"renewables":29.157,"spotPerKwh":19.33277,"channelType":"feedIn","spikeStatus":"none","descriptor":"high"},{"type":"ActualInterval","date":"2025-03-22","duration":30,"startTime":"2025-03-21T16:30:01Z","endTime":"2025-03-21T17:00:00Z","nemTime":"2025-03-22T03:00:00+10:00","perKwh":-19.3138,"renewables":23.54,"spotPerKwh":19.13085,"channelType":"feedIn","spikeStatus":"none","descriptor":"high"},{"type":"ActualInterval","date":"2025-03-22","duration":30,"startTime":"2025-03-21T17:00:01Z","endTime":"2025-03-21T17:30:00Z","nemTime":"2025-03-22T03:30:00+10:00","perKwh":-18.82466,"renewables":23.493,"spotPerKwh":18.64634,"channelType":"feedIn","spikeStatus":"none","descriptor":"high"},{"type":"ActualInterval","date":"2025-03-22","duration":30,"startTime":"2025-03-21T17:30:01Z","endTime":"2025-03-21T18:00:00Z","nemTime":"2025-03-22T04:00:00+10:00","perKwh":-18.17994,"renewables":25.734,"spotPerKwh":18.00773,"channelType":"feedIn","spikeStatus":"none","descriptor":"high"},{"type":"ActualInterval","date":"2025-03-22","duration":30,"startTime":"2025-03-21T18:00:01Z","endTime":"2025-03-21T18:30:00Z","nemTime":"2025-03-22T04:30:00+10:00","perKwh":-16.68887,"renewables":26.806,"spotPerKwh":16.53078,"channelType":"feedIn","spikeStatus":"none","descriptor":"high"},{"type":"ActualInterval","date":"2025-03-22","duration":30,"startTime":"2025-03-21T18:30:01Z","endTime":"2025-03-21T19:00:00Z","nemTime":"2025-03-22T05:00:00+10:00","perKwh":-17.85732,"renewables":26.136,"spotPerKwh":17.68816,"channelType":"feedIn","spikeStatus":"none","descriptor":"high"},{"type":"ActualInterval","date":"2025-03-22","duration":30,"startTime":"2025-03-21T19:00:01Z","endTime":"2025-03-21T19:30:00Z","nemTime":"2025-03-22T05:30:00+10:00","perKwh":-15.24488,"renewables":21.911,"spotPerKwh":15.10047,"channelType":"feedIn","spikeStatus":"none","descriptor":"high"},{"type":"ActualInterval","date":"2025-03-22","duration":30,"startTime":"2025-03-21T19:30:01Z","endTime":"2025-03-21T20:00:00Z","nemTime":"2025-03-22T06:00:00+10:00","perKwh":-17.74719,"renewables":18.847,"spotPerKwh":17.57908,"channelType":"feedIn","spikeStatus":"none","descriptor":"high"},{"type":"ActualInterval","date":"2025-03-22","duration":30,"startTime":"2025-03-21T20:00:01Z","endTime":"2025-03-21T20:30:00Z","nemTime":"2025-03-22T06:30:00+10:00","perKwh":-19.58696,"renewables":15.495999999999999,"spotPerKwh":19.40142,"channelType":"feedIn","spikeStatus":"none","descriptor":"high"},{"type":"ActualInterval","date":"2025-03-22","duration":30,"startTime":"2025-03-21T20:30:01Z","endTime":"2025-03-21T21:00:00Z","nemTime":"2025-03-22T07:00:00+10:00","perKwh":-17.45862,"renewables":15.795,"spotPerKwh":17.29324,"channelType":"feedIn","spikeStatus":"none","descriptor":"high"},{"type":"ActualInterval","date":"2025-03-22","duration":30,"startTime":"2025-03-21T21:00:01Z","endTime":"2025-03-21T21:30:00Z","nemTime":"2025-03-22T07:30:00+10:00","perKwh":-12.88752,"renewables":23.954,"spotPerKwh":12.76544,"channelType":"feedIn","spikeStatus":"none","descriptor":"high"},{"type":"ActualInterval","date":"2025-03-22","duration":30,"startTime":"2025-03-21T21:30:01Z","endTime":"2025-03-21T22:00:00Z","nemTime":"2025-03-22T08:00:00+10:00","perKwh":-7.95514,"renewables":36.592999999999996,"spotPerKwh":7.87978,"channelType":"feedIn","spikeStatus":"none","descriptor":"high"},{"type":"ActualInterval","date":"2025-03-22","duration":30,"startTime":"2025-03-21T22:00:01Z","endTime":"2025-03-21T22:30:00Z","nemTime":"2025-03-22T08:30:00+10:00","perKwh":-10.23621,"renewables":54.668000000000006,"spotPerKwh":10.13925,"channelType":"feedIn","spikeStatus":"none","descriptor":"high"},{"type":"ActualInterval","date":"2025-03-22","duration":30,"startTime":"2025-03-21T22:30:01Z","endTime":"2025-03-21T23:00:00Z","nemTime":"2025-03-22T09:00:00+10:00","perKwh":0.72521,"renewables":70.24000000000001,"spotPerKwh":-0.71834,"channelType":"feedIn","spikeStatus":"none","descriptor":"extremelyLow"},{"type":"ActualInterval","date":"2025-03-22","duration":30,"startTime":"2025-03-21T23:00:01Z","endTime":"2025-03-21T23:30:00Z","nemTime":"2025-03-22T09:30:00+10:00","perKwh":3.04094,"renewables":81.862,"spotPerKwh":-3.01213,"channelType":"feedIn","spikeStatus":"none","descriptor":"extremelyLow"},{"type":"ActualInterval","date":"2025-03-22","duration":30,"startTime":"2025-03-21T23:30:01Z","endTime":"2025-03-22T00:00:00Z","nemTime":"2025-03-22T10:00:00+10:00","perKwh":9.69021,"renewables":84.33500000000001,"spotPerKwh":-9.59842,"channelType":"feedIn","spikeStatus":"none","descriptor":"extremelyLow"},{"type":"ActualInterval","date":"2025-03-22","duration":30,"startTime":"2025-03-22T00:00:01Z","endTime":"2025-03-22T00:30:00Z","nemTime":"2025-03-22T10:30:00+10:00","perKwh":6.14838,"renewables":91.228,"spotPerKwh":-6.09014,"channelType":"feedIn","spikeStatus":"none","descriptor":"extremelyLow"},{"type":"ActualInterval","date":"2025-03-22","duration":30,"startTime":"2025-03-22T00:30:01Z","endTime":"2025-03-22T01:00:00Z","nemTime":"2025-03-22T11:00:00+10:00","perKwh":9.95636,"renewables":81.142,"spotPerKwh":-9.86205,"channelType":"feedIn","spikeStatus":"none","descriptor":"extremelyLow"},{"type":"ActualInterval","date":"2025-03-22","duration":30,"startTime":"2025-03-22T01:00:01Z","endTime":"2025-03-22T01:30:00Z","nemTime":"2025-03-22T11:30:00+10:00","perKwh":7.11028,"renewables":83.98400000000001,"spotPerKwh":-7.04293,"channelType":"feedIn","spikeStatus":"none","descriptor":"extremelyLow"},{"type":"ActualInterval","date":"2025-03-22","duration":30,"startTime":"2025-03-22T01:30:01Z","endTime":"2025-03-22T02:00:00Z","nemTime":"2025-03-22T12:00:00+10:00","perKwh":5.7061,"renewables":88.98,"spotPerKwh":-5.65205,"channelType":"feedIn","spikeStatus":"none","descriptor":"extremelyLow"},{"type":"ActualInterval","date":"2025-03-22","duration":30,"startTime":"2025-03-22T02:00:01Z","endTime":"2025-03-22T02:30:00Z","nemTime":"2025-03-22T12:30:00+10:00","perKwh":9.87424,"renewables":89.29599999999999,"spotPerKwh":-9.78071,"channelType":"feedIn","spikeStatus":"none","descriptor":"extremelyLow"},{"type":"ActualInterval","date":"2025-03-22","duration":30,"startTime":"2025-03-22T02:30:01Z","endTime":"2025-03-22T03:00:00Z","nemTime":"2025-03-22T13:00:00+10:00","perKwh":5.22031,"renewables":94.172,"spotPerKwh":-5.17086,"channelType":"feedIn","spikeStatus":"none","descriptor":"extremelyLow"},{"type":"ActualInterval","date":"2025-03-22","duration":30,"startTime":"2025-03-22T03:00:01Z","endTime":"2025-03-22T03:30:00Z","nemTime":"2025-03-22T13:30:00+10:00","perKwh":6.13069,"renewables":95.36200000000001,"spotPerKwh":-6.07262,"channelType":"feedIn","spikeStatus":"none","descriptor":"extremelyLow"},{"type":"ActualInterval","date":"2025-03-22","duration":30,"startTime":"2025-03-22T03:30:01Z","endTime":"2025-03-22T04:00:00Z","nemTime":"2025-03-22T14:00:00+10:00","perKwh":6.64144,"renewables":95.854,"spotPerKwh":-6.57853,"channelType":"feedIn","spikeStatus":"none","descriptor":"extremelyLow"},{"type":"ActualInterval","date":"2025-03-22","duration":30,"startTime":"2025-03-22T04:00:01Z","endTime":"2025-03-22T04:30:00Z","nemTime":"2025-03-22T14:30:00+10:00","perKwh":5.48666,"renewables":92.023,"spotPerKwh":-5.43469,"channelType":"feedIn","spikeStatus":"none","descriptor":"extremelyLow"},{"type":"ActualInterval","date":"2025-03-22","duration":30,"startTime":"2025-03-22T04:30:01Z","endTime":"2025-03-22T05:00:00Z","nemTime":"2025-03-22T15:00:00+10:00","perKwh":3.72358,"renewables":95.095,"spotPerKwh":-3.68831,"channelType":"feedIn","spikeStatus":"none","descriptor":"extremelyLow"},{"type":"ActualInterval","date":"2025-03-22","duration":30,"startTime":"2025-03-22T05:00:01Z","endTime":"2025-03-22T05:30:00Z","nemTime":"2025-03-22T15:30:00+10:00","perKwh":2.73503,"renewables":98.804,"spotPerKwh":-2.70912,"channelType":"feedIn","spikeStatus":"none","descriptor":"extremelyLow"},{"type":"ActualInterval","date":"2025-03-22","duration":30,"startTime":"2025-03-22T05:30:01Z","endTime":"2025-03-22T06:00:00Z","nemTime":"2025-03-22T16:00:00+10:00","perKwh":0.28417,"renewables":104.119,"spotPerKwh":-0.28148,"channelType":"feedIn","spikeStatus":"none","descriptor":"low"},{"type":"ActualInterval","date":"2025-03-22","duration":30,"startTime":"2025-03-22T06:00:01Z","endTime":"2025-03-22T06:30:00Z","nemTime":"2025-03-22T16:30:00+10:00","perKwh":-5.33351,"renewables":101.64999999999999,"spotPerKwh":5.28299,"channelType":"feedIn","spikeStatus":"none","descriptor":"high"},{"type":"ActualInterval","date":"2025-03-22","duration":30,"startTime":"2025-03-22T06:30:01Z","endTime":"2025-03-22T07:00:00Z","nemTime":"2025-03-22T17:00:00+10:00","perKwh":-8.57427,"renewables":85.004,"spotPerKwh":8.49305,"channelType":"feedIn","spikeStatus":"none","descriptor":"high"},{"type":"ActualInterval","date":"2025-03-22","duration":30,"startTime":"2025-03-22T07:00:01Z","endTime":"2025-03-22T07:30:00Z","nemTime":"2025-03-22T17:30:00+10:00","perKwh":-15.26409,"renewables":73.882,"spotPerKwh":15.1195,"channelType":"feedIn","spikeStatus":"none","descriptor":"high"},{"type":"ActualInterval","date":"2025-03-22","duration":30,"startTime":"2025-03-22T07:30:01Z","endTime":"2025-03-22T08:00:00Z","nemTime":"2025-03-22T18:00:00+10:00","perKwh":-8.57785,"renewables":57.706999999999994,"spotPerKwh":8.4966,"channelType":"feedIn","spikeStatus":"none","descriptor":"high"},{"type":"ActualInterval","date":"2025-03-22","duration":30,"startTime":"2025-03-22T08:00:01Z","endTime":"2025-03-22T08:30:00Z","nemTime":"2025-03-22T18:30:00+10:00","perKwh":-17.18353,"renewables":46.798,"spotPerKwh":17.02076,"channelType":"feedIn","spikeStatus":"none","descriptor":"high"},{"type":"ActualInterval","date":"2025-03-22","duration":30,"startTime":"2025-03-22T08:30:01Z","endTime":"2025-03-22T09:00:00Z","nemTime":"2025-03-22T19:00:00+10:00","perKwh":-17.86274,"renewables":41.386,"spotPerKwh":17.69353,"channelType":"feedIn","spikeStatus":"none","descriptor":"high"},{"type":"ActualInterval","date":"2025-03-22","duration":30,"startTime":"2025-03-22T09:00:01Z","endTime":"2025-03-22T09:30:00Z","nemTime":"2025-03-22T19:30:00+10:00","perKwh":-15.52368,"renewables":43.663999999999994,"spotPerKwh":15.37663,"channelType":"feedIn","spikeStatus":"none","descriptor":"high"},{"type":"ActualInterval","date":"2025-03-22","duration":30,"startTime":"2025-03-22T09:30:01Z","endTime":"2025-03-22T10:00:00Z","nemTime":"2025-03-22T20:00:00+10:00","perKwh":-15.02789,"renewables":48.479,"spotPerKwh":14.88554,"channelType":"feedIn","spikeStatus":"none","descriptor":"high"},{"type":"ActualInterval","date":"2025-03-22","duration":30,"startTime":"2025-03-22T10:00:01Z","endTime":"2025-03-22T10:30:00Z","nemTime":"2025-03-22T20:30:00+10:00","perKwh":-12.72179,"renewables":54.806999999999995,"spotPerKwh":12.60128,"channelType":"feedIn","spikeStatus":"none","descriptor":"high"},{"type":"ActualInterval","date":"2025-03-22","duration":30,"startTime":"2025-03-22T10:30:01Z","endTime":"2025-03-22T11:00:00Z","nemTime":"2025-03-22T21:00:00+10:00","perKwh":-12.13533,"renewables":56.058,"spotPerKwh":12.02038,"channelType":"feedIn","spikeStatus":"none","descriptor":"high"},{"type":"ActualInterval","date":"2025-03-22","duration":30,"startTime":"2025-03-22T11:00:01Z","endTime":"2025-03-22T11:30:00Z","nemTime":"2025-03-22T21:30:00+10:00","perKwh":-12.52139,"renewables":56.389,"spotPerKwh":12.40278,"channelType":"feedIn","spikeStatus":"none","descriptor":"high"},{"type":"ActualInterval","date":"2025-03-22","duration":30,"startTime":"2025-03-22T11:30:01Z","endTime":"2025-03-22T12:00:00Z","nemTime":"2025-03-22T22:00:00+10:00","perKwh":-10.99062,"renewables":59.829,"spotPerKwh":10.88651,"channelType":"feedIn","spikeStatus":"none","descriptor":"high"},{"type":"ActualInterval","date":"2025-03-22","duration":30,"startTime":"2025-03-22T12:00:01Z","endTime":"2025-03-22T12:30:00Z","nemTime":"2025-03-22T22:30:00+10:00","perKwh":-10.5778,"renewables":58.498000000000005,"spotPerKwh":10.4776,"channelType":"feedIn","spikeStatus":"none","descriptor":"high"},{"type":"ActualInterval","date":"2025-03-22","duration":30,"startTime":"2025-03-22T12:30:01Z","endTime":"2025-03-22T13:00:00Z","nemTime":"2025-03-22T23:00:00+10:00","perKwh":-12.33543,"renewables":55.593,"spotPerKwh":12.21858,"channelType":"feedIn","spikeStatus":"none","descriptor":"high"},{"type":"ActualInterval","date":"2025-03-22","duration":30,"startTime":"2025-03-22T13:00:01Z","endTime":"2025-03-22T13:30:00Z","nemTime":"2025-03-22T23:30:00+10:00","perKwh":-12.18114,"renewables":54.237,"spotPerKwh":12.06575,"channelType":"feedIn","spikeStatus":"none","descriptor":"high"},{"type":"ActualInterval","date":"2025-03-22","duration":30,"startTime":"2025-03-22T13:30:01Z","endTime":"2025-03-22T14:00:00Z","nemTime":"2025-03-23T00:00:00+10:00","perKwh":-12.02009,"renewables":53.825,"spotPerKwh":11.90623,"channelType":"feedIn","spikeStatus":"none","descriptor":"high"}]